vibegui/__init__.py
vibegui/backend.py
vibegui/config_loader.py
vibegui/config_validator.py
vibegui/exceptions.py
vibegui/utils.py
vibegui/flet/__init__.py
vibegui/flet/flet_gui_builder.py
vibegui/flet/flet_widget_factory.py
vibegui/gtk/__init__.py
vibegui/gtk/gtk_gui_builder.py
vibegui/gtk/gtk_widget_factory.py
vibegui/qt/__init__.py
vibegui/qt/qt_gui_builder.py
vibegui/qt/qt_widget_factory.py
vibegui/schema/gui_config_schema.json
vibegui/tk/__init__.py
vibegui/tk/tk_gui_builder.py
vibegui/tk/tk_widget_factory.py
vibegui/wx/__init__.py
vibegui/wx/wx_gui_builder.py
vibegui/wx/wx_widget_factory.py
vibegui-1.0.4.dist-info/licenses/LICENSE
vibegui-1.0.4.dist-info/METADATA
vibegui-1.0.4.dist-info/WHEEL
vibegui-1.0.4.dist-info/top_level.txt
vibegui-1.0.4.dist-info/RECORD
