Metadata-Version: 2.4
Name: vibegui
Version: 1.0.4
Summary: A Python library to create simple GUIs and read/write config data using multiple backends (Qtpy/PySide6/PyQt, WxPython, TKinter, GTK3/GTK4, and Flet) using a JSON schema.
Author: Jacob Williams
Maintainer: Jacob Williams
License-Expression: MIT
Project-URL: Homepage, https://github.com/jacobwilliams/vibegui
Project-URL: Documentation, https://github.com/jacobwilliams/vibegui/blob/main/README.md
Project-URL: Repository, https://github.com/jacobwilliams/vibegui
Project-URL: Issues, https://github.com/jacobwilliams/vibegui/issues
Project-URL: Changelog, https://github.com/jacobwilliams/vibegui/blob/main/CHANGELOG.md
Keywords: gui,json,configuration,form,builder,qt,pyside6,pyqt6,qtpy,wxpython,tkinter,gtk,gtk3,gtk4,flet,material-design,cross-platform,desktop
Classifier: Development Status :: 4 - Beta
Classifier: Intended Audience :: Developers
Classifier: Operating System :: OS Independent
Classifier: Programming Language :: Python :: 3
Classifier: Programming Language :: Python :: 3.10
Classifier: Programming Language :: Python :: 3.11
Classifier: Programming Language :: Python :: 3.12
Classifier: Programming Language :: Python :: 3.13
Classifier: Topic :: Software Development :: Libraries :: Python Modules
Classifier: Topic :: Software Development :: User Interfaces
Classifier: Topic :: Desktop Environment
Classifier: Topic :: Software Development :: Widget Sets
Requires-Python: >=3.8
License-File: LICENSE
Provides-Extra: pyside6
Requires-Dist: PySide6>=6.5.0; extra == "pyside6"
Requires-Dist: qtpy>=2.0.0; extra == "pyside6"
Provides-Extra: pyqt6
Requires-Dist: PyQt6>=6.5.0; extra == "pyqt6"
Requires-Dist: qtpy>=2.0.0; extra == "pyqt6"
Provides-Extra: qt
Requires-Dist: qtpy>=2.0.0; extra == "qt"
Provides-Extra: wxpython
Requires-Dist: wxPython>=4.2.0; extra == "wxpython"
Provides-Extra: gtk
Requires-Dist: PyGObject>=3.42.0; extra == "gtk"
Provides-Extra: gtk3
Requires-Dist: PyGObject>=3.42.0; extra == "gtk3"
Provides-Extra: gtk4
Requires-Dist: PyGObject>=3.42.0; extra == "gtk4"
Provides-Extra: flet
Requires-Dist: flet>=0.24.0; extra == "flet"
Provides-Extra: all
Requires-Dist: qtpy>=2.0.0; extra == "all"
Requires-Dist: PySide6>=6.5.0; extra == "all"
Requires-Dist: wxPython>=4.2.0; extra == "all"
Requires-Dist: PyGObject>=3.42.0; extra == "all"
Requires-Dist: flet>=0.24.0; extra == "all"
Provides-Extra: dev
Requires-Dist: pytest>=6.0; extra == "dev"
Requires-Dist: pytest-qt>=4.0; extra == "dev"
Requires-Dist: black>=21.0; extra == "dev"
Requires-Dist: flake8>=3.8; extra == "dev"
Requires-Dist: mypy>=0.910; extra == "dev"
Requires-Dist: pre-commit>=2.15.0; extra == "dev"
Requires-Dist: PySide6>=6.5.0; extra == "dev"
Requires-Dist: qtpy>=2.0.0; extra == "dev"
Requires-Dist: wxPython>=4.2.0; extra == "dev"
Requires-Dist: PyGObject>=3.42.0; extra == "dev"
Requires-Dist: flet>=0.24.0; extra == "dev"
Provides-Extra: test
Requires-Dist: pytest>=6.0; extra == "test"
Requires-Dist: pytest-qt>=4.0; extra == "test"
Requires-Dist: pytest-cov>=3.0.0; extra == "test"
Provides-Extra: docs
Requires-Dist: sphinx>=4.0.0; extra == "docs"
Requires-Dist: sphinx-rtd-theme>=1.0.0; extra == "docs"
Requires-Dist: furo>=2021.5.28; extra == "docs"
Requires-Dist: sphinx-autobuild>=2021.3.14; extra == "docs"
Dynamic: license-file
